omu_chat_twitcasting/__init__.py
omu_chat_twitcasting/api.py
omu_chat_twitcasting/chat.py
omu_chat_twitcasting/const.py
omu_chat_twitcasting/salt.py
omu_chat_twitcasting/token.py
omu_chat_twitcasting/twitcasting.py
omu_chat_twitcasting/version.py
omu_chat_twitcasting/types/__init__.py
omu_chat_twitcasting/types/events.py
omu_chat_twitcasting/types/movieinfo.py
omu_chat_twitcasting/types/types.py
omu_chat_twitcasting-0.8.9.dist-info/METADATA
omu_chat_twitcasting-0.8.9.dist-info/WHEEL
omu_chat_twitcasting-0.8.9.dist-info/entry_points.txt
omu_chat_twitcasting-0.8.9.dist-info/RECORD
