Metadata-Version: 2.4
Name: omu_chat_twitcasting
Version: 0.8.9
Summary: TwitCastingを使えるようにするOMUAPPSプラグイン
Author-email: am230 <111672334+am230@users.noreply.github.com>
Requires-Python: >=3.12
Requires-Dist: loguru>=0.7.2
Requires-Dist: omu-chatprovider>=0.8.9
